[
  {
    "text": "welche nahrungsmittel haben den größten positiven einfluss auf das klima?",
    "entities": [
      {
        "start": 40,
        "end": 49,
        "value": "positive_for_climate",
        "entity": "influence_type_on_climate"
      }
    ],
    "predicted_entities": [
      {
        "entity": "topic",
        "start": 7,
        "end": 21,
        "confidence_entity": 0.7069668769836426,
        "value": "nahrungsmittel",
        "extractor": "DIETClassifier"
      }
    ]
  },
  {
    "text": "was kann ich daheim tun?",
    "entities": [
      {
        "start": 13,
        "end": 19,
        "value": "haushalt",
        "entity": "topic"
      }
    ],
    "predicted_entities": []
  },
  {
    "text": "welche folgen hat der klimawandel für die landwirtschaft?",
    "entities": [
      {
        "start": 42,
        "end": 56,
        "value": "nahrungsmittel",
        "entity": "topic"
      }
    ],
    "predicted_entities": [
      {
        "entity": "consequence_category",
        "start": 42,
        "end": 56,
        "confidence_entity": 0.9220935702323914,
        "value": "nahrungsmittel",
        "extractor": "DIETClassifier",
        "processors": [
          "EntitySynonymMapper"
        ]
      }
    ]
  },
  {
    "text": "welche wirtschaftlichen folgen hat der klimawandel?",
    "entities": [
      {
        "start": 7,
        "end": 23,
        "value": "wirtschaft",
        "entity": "consequence_category"
      }
    ],
    "predicted_entities": []
  },
  {
    "text": "wie wirkt sich der klimawandel auf die tiere aus?",
    "entities": [
      {
        "start": 39,
        "end": 44,
        "value": "tier",
        "entity": "consequence_category"
      }
    ],
    "predicted_entities": [
      {
        "entity": "topic",
        "start": 39,
        "end": 44,
        "confidence_entity": 0.4113909602165222,
        "value": "tier",
        "extractor": "DIETClassifier",
        "processors": [
          "EntitySynonymMapper"
        ]
      }
    ]
  },
  {
    "text": "welche folgen hat der klimawandel für die gesundheit aus?",
    "entities": [
      {
        "start": 42,
        "end": 52,
        "value": "gesundheit",
        "entity": "consequence_category"
      }
    ],
    "predicted_entities": [
      {
        "entity": "topic",
        "start": 42,
        "end": 52,
        "confidence_entity": 0.6751340627670288,
        "value": "gesundheit",
        "extractor": "DIETClassifier"
      }
    ]
  },
  {
    "text": "wie konsumiere ich umweltfreundlich?",
    "entities": [
      {
        "start": 4,
        "end": 14,
        "value": "konsum",
        "entity": "topic"
      }
    ],
    "predicted_entities": []
  },
  {
    "text": "welche folgen hat der klimawandel für die produktion von essen",
    "entities": [
      {
        "start": 57,
        "end": 62,
        "value": "nahrungsmittel",
        "entity": "topic"
      }
    ],
    "predicted_entities": []
  },
  {
    "text": "welche auswirkung hat der klimawandel auf die energie",
    "entities": [
      {
        "start": 46,
        "end": 53,
        "value": "energie",
        "entity": "consequence_category"
      }
    ],
    "predicted_entities": [
      {
        "entity": "topic",
        "start": 46,
        "end": 53,
        "confidence_entity": 0.4678105115890503,
        "value": "energie",
        "extractor": "DIETClassifier"
      }
    ]
  },
  {
    "text": "was sind die folgen des klimawandels für die antarktis",
    "entities": [
      {
        "start": 45,
        "end": 54,
        "value": "arktis",
        "entity": "consequence_category"
      }
    ],
    "predicted_entities": [
      {
        "entity": "greenhouse_gas",
        "start": 45,
        "end": 54,
        "confidence_entity": 0.7441136837005615,
        "value": "arktis",
        "extractor": "DIETClassifier",
        "processors": [
          "EntitySynonymMapper"
        ]
      }
    ]
  },
  {
    "text": "welche lebensmittel haben den größten negativen einfluss auf das klima?",
    "entities": [
      {
        "start": 38,
        "end": 47,
        "value": "negative_for_climate",
        "entity": "influence_type_on_climate"
      }
    ],
    "predicted_entities": []
  },
  {
    "text": "welche lebensmittel tragen am meisten zum klimawandel bei?",
    "entities": [
      {
        "start": 42,
        "end": 53,
        "value": "negative_for_climate",
        "entity": "influence_type_on_climate"
      }
    ],
    "predicted_entities": []
  },
  {
    "text": "konsum bitte",
    "entities": [
      {
        "start": 0,
        "end": 6,
        "value": "konsum",
        "entity": "topic"
      }
    ],
    "predicted_entities": []
  },
  {
    "text": "was kann ich zu hause tun?",
    "entities": [
      {
        "start": 16,
        "end": 21,
        "value": "haushalt",
        "entity": "topic"
      }
    ],
    "predicted_entities": []
  },
  {
    "text": "was sind die folgen des klimawandels für die nahrungsmittel produktion?",
    "entities": [
      {
        "start": 45,
        "end": 59,
        "value": "nahrungsmittel",
        "entity": "topic"
      }
    ],
    "predicted_entities": []
  },
  {
    "text": "was sind die folgen des klimawandels für die arktis?",
    "entities": [
      {
        "start": 45,
        "end": 51,
        "value": "arktis",
        "entity": "consequence_category"
      }
    ],
    "predicted_entities": []
  },
  {
    "text": "welches sind die besten lebensmittel?",
    "entities": [
      {
        "start": 17,
        "end": 23,
        "value": "positive_for_climate",
        "entity": "influence_type_on_climate"
      }
    ],
    "predicted_entities": []
  },
  {
    "text": "welche nahrungsmittel sollte ich wegen ihrer klimaschädlichen wirkung vermeiden?",
    "entities": [
      {
        "start": 70,
        "end": 79,
        "value": "negative_for_climate",
        "entity": "influence_type_on_climate"
      }
    ],
    "predicted_entities": [
      {
        "entity": "influence_type_on_climate",
        "start": 45,
        "end": 61,
        "confidence_entity": 0.9889143109321594,
        "value": "negative_for_climate",
        "extractor": "DIETClassifier",
        "processors": [
          "EntitySynonymMapper"
        ]
      },
      {
        "entity": "influence_type_on_climate",
        "start": 70,
        "end": 79,
        "confidence_entity": 0.9949988126754761,
        "value": "negative_for_climate",
        "extractor": "DIETClassifier",
        "processors": [
          "EntitySynonymMapper"
        ]
      }
    ]
  },
  {
    "text": "wie viel co2 wird durch den konsum von lamm verursacht?",
    "entities": [
      {
        "start": 39,
        "end": 43,
        "value": "lamm",
        "entity": "meat_type"
      }
    ],
    "predicted_entities": [
      {
        "entity": "topic",
        "start": 28,
        "end": 34,
        "confidence_entity": 0.9935176372528076,
        "value": "konsum",
        "extractor": "DIETClassifier"
      },
      {
        "entity": "meat_type",
        "start": 39,
        "end": 43,
        "confidence_entity": 0.9979786276817322,
        "value": "lamm",
        "extractor": "DIETClassifier"
      }
    ]
  },
  {
    "text": "ich möchte gerne mehr über nahrungsmittel erfahren",
    "entities": [
      {
        "start": 27,
        "end": 41,
        "value": "nahrungsmittel",
        "entity": "topic"
      }
    ],
    "predicted_entities": []
  },
  {
    "text": "welche auswirkung hat der klimawandel auf die energieversorgung?",
    "entities": [
      {
        "start": 46,
        "end": 63,
        "value": "energie",
        "entity": "consequence_category"
      }
    ],
    "predicted_entities": []
  },
  {
    "text": "welche lebensmittel sind besonders klimaschädlich?",
    "entities": [
      {
        "start": 35,
        "end": 49,
        "value": "negative_for_climate",
        "entity": "influence_type_on_climate"
      }
    ],
    "predicted_entities": []
  },
  {
    "text": "kannst du mir mehr über essen erzählen?",
    "entities": [
      {
        "start": 24,
        "end": 29,
        "value": "nahrungsmittel",
        "entity": "topic"
      }
    ],
    "predicted_entities": []
  }
]